{"cameraMode":{"drawMode":2,"name":"Shaded Wireframe","section":"Shading Mode"},"sceneLighting":false,"audioPlay":false,"sceneViewState":{"m_AlwaysRefresh":false,"showFog":true,"showSkybox":false,"showFlares":true,"showImageEffects":true,"showParticleSystems":true,"showVisualEffectGraphs":true,"m_FxEnabled":true},"in2DMode":false,"pivot":{"x":-12.738672256469727,"y":-5.240750312805176,"z":3.9130992889404299},"rotation":{"x":0.23067118227481843,"y":-0.47008216381073,"z":0.12820401787757874,"w":0.8424851894378662},"size":10.0,"orthographic":false}